README.md
setup.cfg
setup.py
src/nrmc/biconnected.pyx
src/nrmc.egg-info/PKG-INFO
src/nrmc.egg-info/SOURCES.txt
src/nrmc.egg-info/dependency_links.txt
src/nrmc.egg-info/not-zip-safe
src/nrmc.egg-info/top_level.txt